[
    {
        "data": [
            {
                "y": 3.309930431430424e-05, 
                "x": 0.0
            }, 
            {
                "y": 0.000474158368895211, 
                "x": 1.0
            }, 
            {
                "y": 0.00046816479400749064, 
                "x": 2.0
            }, 
            {
                "y": 0.0004512635379061372, 
                "x": 3.0
            }, 
            {
                "y": 0.003504161191414805, 
                "x": 4.0
            }, 
            {
                "y": 0.006855575868372943, 
                "x": 5.0
            }, 
            {
                "y": 0.0031097290093291866, 
                "x": 6.0
            }, 
            {
                "y": 0.0009037505648441031, 
                "x": 7.0
            }, 
            {
                "y": 0.0019166267369429804, 
                "x": 8.0
            }, 
            {
                "y": 0.0150166444252174, 
                "x": 9.0
            }, 
            {
                "y": 0.015797032072762087, 
                "x": 10.0
            }, 
            {
                "y": 0.001441614608361365, 
                "x": 11.0
            }, 
            {
                "y": 0.002239140170174653, 
                "x": 12.0
            }, 
            {
                "y": 0.0004655493482309126, 
                "x": 13.0
            }, 
            {
                "y": 0.0004928536224741252, 
                "x": 14.0
            }, 
            {
                "y": 0.0004649000464900045, 
                "x": 15.0
            }, 
            {
                "y": 0.00047551117451260106, 
                "x": 16.0
            }, 
            {
                "y": 0.0004921259842519685, 
                "x": 17.0
            }, 
            {
                "y": 0.0013489208633093524, 
                "x": 18.0
            }, 
            {
                "y": 0.010978215104402205, 
                "x": 19.0
            }, 
            {
                "y": 0.01017457265280785, 
                "x": 20.0
            }, 
            {
                "y": 0.012974051896207584, 
                "x": 21.0
            }, 
            {
                "y": 0.016218955904713638, 
                "x": 22.0
            }, 
            {
                "y": 0.06962576153176674, 
                "x": 23.0
            }, 
            {
                "y": 0.13234010800693066, 
                "x": 24.0
            }, 
            {
                "y": 0.1209361946648397, 
                "x": 25.0
            }, 
            {
                "y": 0.11324114458306567, 
                "x": 26.0
            }, 
            {
                "y": 0.06536371162221502, 
                "x": 27.0
            }, 
            {
                "y": 0.10667108368876557, 
                "x": 28.0
            }, 
            {
                "y": 0.16251173195849783, 
                "x": 29.0
            }, 
            {
                "y": 0.13850758081670006, 
                "x": 30.0
            }, 
            {
                "y": 0.15622785817585338, 
                "x": 31.0
            }, 
            {
                "y": 0.052376587665313605, 
                "x": 32.0
            }, 
            {
                "y": 0.11636363636363636, 
                "x": 33.0
            }, 
            {
                "y": 0.19529744314531675, 
                "x": 34.0
            }, 
            {
                "y": 0.2600540882364813, 
                "x": 35.0
            }, 
            {
                "y": 0.3198618397812464, 
                "x": 36.0
            }, 
            {
                "y": 0.36040902951958315, 
                "x": 37.0
            }, 
            {
                "y": 0.21875137644581868, 
                "x": 38.0
            }, 
            {
                "y": 0.17762145526489337, 
                "x": 39.0
            }, 
            {
                "y": 0.18677447836795386, 
                "x": 40.0
            }, 
            {
                "y": 0.22799532148328752, 
                "x": 41.0
            }, 
            {
                "y": 0.21605962625243072, 
                "x": 42.0
            }, 
            {
                "y": 0.21060812123567124, 
                "x": 43.0
            }, 
            {
                "y": 0.18756968557866907, 
                "x": 44.0
            }, 
            {
                "y": 0.2493229700096135, 
                "x": 45.0
            }, 
            {
                "y": 0.4160308909164513, 
                "x": 46.0
            }, 
            {
                "y": 0.2949064621157773, 
                "x": 47.0
            }, 
            {
                "y": 0.2603956700261292, 
                "x": 48.0
            }, 
            {
                "y": 0.22555505149334074, 
                "x": 49.0
            }, 
            {
                "y": 0.1848478115974228, 
                "x": 50.0
            }, 
            {
                "y": 0.2908814372965137, 
                "x": 51.0
            }, 
            {
                "y": 0.13979686520376175, 
                "x": 52.0
            }, 
            {
                "y": 0.04570762802056843, 
                "x": 53.0
            }, 
            {
                "y": 0.17567122772370342, 
                "x": 54.0
            }, 
            {
                "y": 0.1228171811636183, 
                "x": 55.0
            }, 
            {
                "y": 0.2631549302121236, 
                "x": 56.0
            }, 
            {
                "y": 0.24452002457186525, 
                "x": 57.0
            }, 
            {
                "y": 0.04458981220739392, 
                "x": 58.0
            }, 
            {
                "y": 0.13348137922756054, 
                "x": 59.0
            }, 
            {
                "y": 0.13550896412050353, 
                "x": 60.0
            }, 
            {
                "y": 0.13798209194137362, 
                "x": 61.0
            }, 
            {
                "y": 0.09283149354967415, 
                "x": 62.0
            }, 
            {
                "y": 0.06790811183617167, 
                "x": 63.0
            }, 
            {
                "y": 0.13903824308973875, 
                "x": 64.0
            }, 
            {
                "y": 0.1779034519116713, 
                "x": 65.0
            }, 
            {
                "y": 0.1883058936123434, 
                "x": 66.0
            }, 
            {
                "y": 0.19972141862209364, 
                "x": 67.0
            }, 
            {
                "y": 0.22583903343348466, 
                "x": 68.0
            }, 
            {
                "y": 0.20660470230256847, 
                "x": 69.0
            }, 
            {
                "y": 0.23789339141549173, 
                "x": 70.0
            }, 
            {
                "y": 0.2516887202738966, 
                "x": 71.0
            }, 
            {
                "y": 0.23618533699994812, 
                "x": 72.0
            }, 
            {
                "y": 0.2697830776764562, 
                "x": 73.0
            }, 
            {
                "y": 0.18870800484763675, 
                "x": 74.0
            }, 
            {
                "y": 0.21277374489111206, 
                "x": 75.0
            }, 
            {
                "y": 0.23426864502228095, 
                "x": 76.0
            }, 
            {
                "y": 0.14477641868859034, 
                "x": 77.0
            }, 
            {
                "y": 0.1544334503670603, 
                "x": 78.0
            }, 
            {
                "y": 0.19208484729451047, 
                "x": 79.0
            }, 
            {
                "y": 0.23236758825405393, 
                "x": 80.0
            }, 
            {
                "y": 0.18402300287535941, 
                "x": 81.0
            }, 
            {
                "y": 0.19270006225147052, 
                "x": 82.0
            }, 
            {
                "y": 0.25194823477360256, 
                "x": 83.0
            }, 
            {
                "y": 0.246407874890847, 
                "x": 84.0
            }, 
            {
                "y": 0.23402252002424836, 
                "x": 85.0
            }, 
            {
                "y": 0.198551433651127, 
                "x": 86.0
            }, 
            {
                "y": 0.2024108878807518, 
                "x": 87.0
            }, 
            {
                "y": 0.18598615916955022, 
                "x": 88.0
            }, 
            {
                "y": 0.1865542557689597, 
                "x": 89.0
            }, 
            {
                "y": 0.16850031161364995, 
                "x": 90.0
            }, 
            {
                "y": 0.21333602697003753, 
                "x": 91.0
            }, 
            {
                "y": 0.2266857599067304, 
                "x": 92.0
            }, 
            {
                "y": 0.2350565428109855, 
                "x": 93.0
            }, 
            {
                "y": 0.27562446167097326, 
                "x": 94.0
            }, 
            {
                "y": 0.19715741008474388, 
                "x": 95.0
            }, 
            {
                "y": 0.28076410484229236, 
                "x": 96.0
            }, 
            {
                "y": 0.26807228915662645, 
                "x": 97.0
            }, 
            {
                "y": 0.2595421743612674, 
                "x": 98.0
            }, 
            {
                "y": 0.2616025838615865, 
                "x": 99.0
            }, 
            {
                "y": 0.2501111754955732, 
                "x": 100.0
            }, 
            {
                "y": 0.23386687331320316, 
                "x": 101.0
            }, 
            {
                "y": 0.24573239292650523, 
                "x": 102.0
            }, 
            {
                "y": 0.3045481018690105, 
                "x": 103.0
            }, 
            {
                "y": 0.27894666553352676, 
                "x": 104.0
            }, 
            {
                "y": 0.2661970720424738, 
                "x": 105.0
            }, 
            {
                "y": 0.3166365401352346, 
                "x": 106.0
            }, 
            {
                "y": 0.2115153938424631, 
                "x": 107.0
            }, 
            {
                "y": 0.18301424669479244, 
                "x": 108.0
            }, 
            {
                "y": 0.1580492093660706, 
                "x": 109.0
            }, 
            {
                "y": 0.19556216685260938, 
                "x": 110.0
            }, 
            {
                "y": 0.26145559574301996, 
                "x": 111.0
            }, 
            {
                "y": 0.23302669668703765, 
                "x": 112.0
            }, 
            {
                "y": 0.2096924925459481, 
                "x": 113.0
            }, 
            {
                "y": 0.23793467867746967, 
                "x": 114.0
            }, 
            {
                "y": 0.25176565301716247, 
                "x": 115.0
            }, 
            {
                "y": 0.24904388756652673, 
                "x": 116.0
            }, 
            {
                "y": 0.22986989188198648, 
                "x": 117.0
            }, 
            {
                "y": 0.29754754098360653, 
                "x": 118.0
            }, 
            {
                "y": 0.27192891827668153, 
                "x": 119.0
            }, 
            {
                "y": 0.2264073555046655, 
                "x": 120.0
            }, 
            {
                "y": 0.202207002530237, 
                "x": 121.0
            }, 
            {
                "y": 0.2876260434056761, 
                "x": 122.0
            }, 
            {
                "y": 0.3474788895783311, 
                "x": 123.0
            }, 
            {
                "y": 0.28076287577011255, 
                "x": 124.0
            }, 
            {
                "y": 0.30468316000258383, 
                "x": 125.0
            }, 
            {
                "y": 0.3691148775894538, 
                "x": 126.0
            }, 
            {
                "y": 0.3444389736856503, 
                "x": 127.0
            }, 
            {
                "y": 0.30808461918763497, 
                "x": 128.0
            }, 
            {
                "y": 0.26081424936386766, 
                "x": 129.0
            }, 
            {
                "y": 0.25568880268801053, 
                "x": 130.0
            }, 
            {
                "y": 0.19687159290657053, 
                "x": 131.0
            }, 
            {
                "y": 0.2007502528582585, 
                "x": 132.0
            }, 
            {
                "y": 0.15744924429721469, 
                "x": 133.0
            }, 
            {
                "y": 0.25650966626499716, 
                "x": 134.0
            }, 
            {
                "y": 0.22986851725058313, 
                "x": 135.0
            }, 
            {
                "y": 0.2216827520871573, 
                "x": 136.0
            }, 
            {
                "y": 0.25974336019098776, 
                "x": 137.0
            }, 
            {
                "y": 0.2764518695306285, 
                "x": 138.0
            }, 
            {
                "y": 0.2582372629230197, 
                "x": 139.0
            }, 
            {
                "y": 0.19322550959950585, 
                "x": 140.0
            }, 
            {
                "y": 0.20224352247020688, 
                "x": 141.0
            }, 
            {
                "y": 0.20513065837469352, 
                "x": 142.0
            }, 
            {
                "y": 0.2236954662104363, 
                "x": 143.0
            }, 
            {
                "y": 0.18738049713193117, 
                "x": 144.0
            }, 
            {
                "y": 0.2516750418760469, 
                "x": 145.0
            }, 
            {
                "y": 0.22504743833017077, 
                "x": 146.0
            }, 
            {
                "y": 0.18900945047252365, 
                "x": 147.0
            }, 
            {
                "y": 0.2272557094721078, 
                "x": 148.0
            }, 
            {
                "y": 0.20482897384305837, 
                "x": 149.0
            }, 
            {
                "y": 0.20079883805374002, 
                "x": 150.0
            }, 
            {
                "y": 0.24154589371980678, 
                "x": 151.0
            }, 
            {
                "y": 0.21590440873506384, 
                "x": 152.0
            }, 
            {
                "y": 0.13557751698579368, 
                "x": 153.0
            }, 
            {
                "y": 0.1567311488353731, 
                "x": 154.0
            }, 
            {
                "y": 0.1291020555355211, 
                "x": 155.0
            }, 
            {
                "y": 0.10963455149501661, 
                "x": 156.0
            }, 
            {
                "y": 0.08663532572196105, 
                "x": 157.0
            }, 
            {
                "y": 0.09232264334305151, 
                "x": 158.0
            }, 
            {
                "y": 0.07994714238519987, 
                "x": 159.0
            }, 
            {
                "y": 0.07926629544710122, 
                "x": 160.0
            }, 
            {
                "y": 0.08589540412044372, 
                "x": 161.0
            }, 
            {
                "y": 0.0690006798096533, 
                "x": 162.0
            }, 
            {
                "y": 0.08317025440313111, 
                "x": 163.0
            }, 
            {
                "y": 0.07201166180758017, 
                "x": 164.0
            }, 
            {
                "y": 0.07486979166666669, 
                "x": 165.0
            }, 
            {
                "y": 0.08200531208499334, 
                "x": 166.0
            }, 
            {
                "y": 0.09670329670329669, 
                "x": 167.0
            }, 
            {
                "y": 0.07962447844228095, 
                "x": 168.0
            }, 
            {
                "y": 0.08507853403141362, 
                "x": 169.0
            }, 
            {
                "y": 0.08302143586253827, 
                "x": 170.0
            }, 
            {
                "y": 0.08429520811472543, 
                "x": 171.0
            }, 
            {
                "y": 0.08573342263898191, 
                "x": 172.0
            }, 
            {
                "y": 0.07910189982728842, 
                "x": 173.0
            }, 
            {
                "y": 0.0882543802725503, 
                "x": 174.0
            }, 
            {
                "y": 0.07646076794657762, 
                "x": 175.0
            }, 
            {
                "y": 0.08872333220453774, 
                "x": 176.0
            }, 
            {
                "y": 0.06949100883876867, 
                "x": 177.0
            }, 
            {
                "y": 0.08094488188976379, 
                "x": 178.0
            }, 
            {
                "y": 0.08179760750080826, 
                "x": 179.0
            }, 
            {
                "y": 0.07274490785645005, 
                "x": 180.0
            }, 
            {
                "y": 0.07973395542760708, 
                "x": 181.0
            }, 
            {
                "y": 0.0766990291262136, 
                "x": 182.0
            }, 
            {
                "y": 0.07500074170037282, 
                "x": 183.0
            }, 
            {
                "y": 0.08107179663345929, 
                "x": 184.0
            }, 
            {
                "y": 0.08387987573351743, 
                "x": 185.0
            }, 
            {
                "y": 0.08453680873547025, 
                "x": 186.0
            }, 
            {
                "y": 0.08663626797614872, 
                "x": 187.0
            }, 
            {
                "y": 0.09787377657779277, 
                "x": 188.0
            }, 
            {
                "y": 0.08083935328517372, 
                "x": 189.0
            }, 
            {
                "y": 0.07569721115537847, 
                "x": 190.0
            }, 
            {
                "y": 0.09512022630834512, 
                "x": 191.0
            }, 
            {
                "y": 0.07531239446133065, 
                "x": 192.0
            }, 
            {
                "y": 0.07814013561511139, 
                "x": 193.0
            }, 
            {
                "y": 0.07987967914438501, 
                "x": 194.0
            }, 
            {
                "y": 0.07643835616438356, 
                "x": 195.0
            }, 
            {
                "y": 0.06806462701959436, 
                "x": 196.0
            }, 
            {
                "y": 0.08226997985224983, 
                "x": 197.0
            }, 
            {
                "y": 0.08750835003340013, 
                "x": 198.0
            }, 
            {
                "y": 0.0885486018641811, 
                "x": 199.0
            }, 
            {
                "y": 0.08265802269043761, 
                "x": 200.0
            }, 
            {
                "y": 0.09109589041095889, 
                "x": 201.0
            }, 
            {
                "y": 0.07813982916798481, 
                "x": 202.0
            }, 
            {
                "y": 0.09182259182259184, 
                "x": 203.0
            }, 
            {
                "y": 0.08469055374592833, 
                "x": 204.0
            }, 
            {
                "y": 0.08300395256916997, 
                "x": 205.0
            }, 
            {
                "y": 0.10557083906464923, 
                "x": 206.0
            }, 
            {
                "y": 0.08973010865755346, 
                "x": 207.0
            }, 
            {
                "y": 0.11004170676932946, 
                "x": 208.0
            }, 
            {
                "y": 0.0835044490075291, 
                "x": 209.0
            }, 
            {
                "y": 0.08832487309644672, 
                "x": 210.0
            }, 
            {
                "y": 0.0924114671163575, 
                "x": 211.0
            }, 
            {
                "y": 0.08648825065274152, 
                "x": 212.0
            }, 
            {
                "y": 0.08236347358997313, 
                "x": 213.0
            }, 
            {
                "y": 0.06567408097142911, 
                "x": 214.0
            }, 
            {
                "y": 0.06566265060240964, 
                "x": 215.0
            }, 
            {
                "y": 0.07098479023605624, 
                "x": 216.0
            }, 
            {
                "y": 0.05809128630705394, 
                "x": 217.0
            }, 
            {
                "y": 0.05333041226223916, 
                "x": 218.0
            }, 
            {
                "y": 0.0544611819235226, 
                "x": 219.0
            }, 
            {
                "y": 0.04297102405476942, 
                "x": 220.0
            }, 
            {
                "y": 0.051317673896078275, 
                "x": 221.0
            }, 
            {
                "y": 0.04379595343638563, 
                "x": 222.0
            }, 
            {
                "y": 0.03907447015360684, 
                "x": 223.0
            }, 
            {
                "y": 0.06542103841295571, 
                "x": 224.0
            }, 
            {
                "y": 0.026677452105224066, 
                "x": 225.0
            }, 
            {
                "y": 0.051845590307128764, 
                "x": 226.0
            }, 
            {
                "y": 0.061676839061998084, 
                "x": 227.0
            }, 
            {
                "y": 0.04806338028169013, 
                "x": 228.0
            }, 
            {
                "y": 0.043534482758620686, 
                "x": 229.0
            }, 
            {
                "y": 0.03971369198799354, 
                "x": 230.0
            }, 
            {
                "y": 0.03577078016577732, 
                "x": 231.0
            }, 
            {
                "y": 0.04264494489698132, 
                "x": 232.0
            }, 
            {
                "y": 0.04913294797687861, 
                "x": 233.0
            }, 
            {
                "y": 0.04031109650564136, 
                "x": 234.0
            }, 
            {
                "y": 0.03956452469463622, 
                "x": 235.0
            }, 
            {
                "y": 0.05076802915907314, 
                "x": 236.0
            }, 
            {
                "y": 0.04601861427094106, 
                "x": 237.0
            }, 
            {
                "y": 0.04708992185743582, 
                "x": 238.0
            }, 
            {
                "y": 0.03652861796184272, 
                "x": 239.0
            }, 
            {
                "y": 0.03699072872679233, 
                "x": 240.0
            }, 
            {
                "y": 0.05205670462468045, 
                "x": 241.0
            }, 
            {
                "y": 0.031065088757396442, 
                "x": 242.0
            }, 
            {
                "y": 0.03968668407310705, 
                "x": 243.0
            }, 
            {
                "y": 0.05340519353258207, 
                "x": 244.0
            }, 
            {
                "y": 0.05111621114124764, 
                "x": 245.0
            }, 
            {
                "y": 0.04037191093711769, 
                "x": 246.0
            }, 
            {
                "y": 0.04726487523992323, 
                "x": 247.0
            }, 
            {
                "y": 0.04764764764764765, 
                "x": 248.0
            }, 
            {
                "y": 0.026082758948143114, 
                "x": 249.0
            }, 
            {
                "y": 0.06269442450346972, 
                "x": 250.0
            }, 
            {
                "y": 0.039959016393442626, 
                "x": 251.0
            }, 
            {
                "y": 0.04659855469723399, 
                "x": 252.0
            }, 
            {
                "y": 0.04896004257395006, 
                "x": 253.0
            }, 
            {
                "y": 0.05096743747050496, 
                "x": 254.0
            }, 
            {
                "y": 0.033088235294117654, 
                "x": 255.0
            }, 
            {
                "y": 0.04160654160654161, 
                "x": 256.0
            }, 
            {
                "y": 0.0365296803652968, 
                "x": 257.0
            }, 
            {
                "y": 0.044956525463657006, 
                "x": 258.0
            }, 
            {
                "y": 0.048799182422074615, 
                "x": 259.0
            }, 
            {
                "y": 0.039856004114168175, 
                "x": 260.0
            }, 
            {
                "y": 0.05518945634266887, 
                "x": 261.0
            }, 
            {
                "y": 0.043001443001443006, 
                "x": 262.0
            }, 
            {
                "y": 0.05571318029404179, 
                "x": 263.0
            }, 
            {
                "y": 0.033123028391167195, 
                "x": 264.0
            }, 
            {
                "y": 0.047354497354497364, 
                "x": 265.0
            }, 
            {
                "y": 0.051145444858817266, 
                "x": 266.0
            }, 
            {
                "y": 0.04485049833887043, 
                "x": 267.0
            }, 
            {
                "y": 0.04357418643132929, 
                "x": 268.0
            }, 
            {
                "y": 0.04970008568980293, 
                "x": 269.0
            }, 
            {
                "y": 0.06758326469408013, 
                "x": 270.0
            }, 
            {
                "y": 0.028748850045998166, 
                "x": 271.0
            }, 
            {
                "y": 0.016235847041230506, 
                "x": 272.0
            }, 
            {
                "y": 0.055006337135614716, 
                "x": 273.0
            }, 
            {
                "y": 0.04057971014492754, 
                "x": 274.0
            }, 
            {
                "y": 0.04462854088722609, 
                "x": 275.0
            }, 
            {
                "y": 0.036647493837304854, 
                "x": 276.0
            }, 
            {
                "y": 0.0324627776421772, 
                "x": 277.0
            }, 
            {
                "y": 0.038461538461538464, 
                "x": 278.0
            }, 
            {
                "y": 0.024459613196814563, 
                "x": 279.0
            }, 
            {
                "y": 0.049811320754716996, 
                "x": 280.0
            }, 
            {
                "y": 0.03491152558584409, 
                "x": 281.0
            }, 
            {
                "y": 0.03893712181004999, 
                "x": 282.0
            }, 
            {
                "y": 0.04674634794156706, 
                "x": 283.0
            }, 
            {
                "y": 0.02875399361022364, 
                "x": 284.0
            }, 
            {
                "y": 0.04885133350937418, 
                "x": 285.0
            }, 
            {
                "y": 0.03640092284029736, 
                "x": 286.0
            }, 
            {
                "y": 0.03948312993539125, 
                "x": 287.0
            }, 
            {
                "y": 0.03699255344703339, 
                "x": 288.0
            }, 
            {
                "y": 0.02650997540311561, 
                "x": 289.0
            }, 
            {
                "y": 0.03512684694730973, 
                "x": 290.0
            }, 
            {
                "y": 0.03538696537678208, 
                "x": 291.0
            }, 
            {
                "y": 0.037446594621764265, 
                "x": 292.0
            }, 
            {
                "y": 0.023538156590683843, 
                "x": 293.0
            }, 
            {
                "y": 0.04129955947136564, 
                "x": 294.0
            }, 
            {
                "y": 0.03715584068430901, 
                "x": 295.0
            }, 
            {
                "y": 0.0330760749724366, 
                "x": 296.0
            }, 
            {
                "y": 0.02942809550249861, 
                "x": 297.0
            }, 
            {
                "y": 0.04440697020798201, 
                "x": 298.0
            }, 
            {
                "y": 0.036354581673306775, 
                "x": 299.0
            }, 
            {
                "y": 0.039383561643835614, 
                "x": 300.0
            }, 
            {
                "y": 0.04027210884353741, 
                "x": 301.0
            }, 
            {
                "y": 0.03873952009251229, 
                "x": 302.0
            }, 
            {
                "y": 0.04120443740095087, 
                "x": 303.0
            }, 
            {
                "y": 0.03901437371663244, 
                "x": 304.0
            }, 
            {
                "y": 0.040748898678414094, 
                "x": 305.0
            }, 
            {
                "y": 0.036912751677852344, 
                "x": 306.0
            }, 
            {
                "y": 0.043453070683661645, 
                "x": 307.0
            }, 
            {
                "y": 0.03860103626943005, 
                "x": 308.0
            }, 
            {
                "y": 0.036637931034482756, 
                "x": 309.0
            }, 
            {
                "y": 0.050080342795929295, 
                "x": 310.0
            }, 
            {
                "y": 0.03672985781990521, 
                "x": 311.0
            }, 
            {
                "y": 0.027741428945302276, 
                "x": 312.0
            }, 
            {
                "y": 0.04518398268398269, 
                "x": 313.0
            }, 
            {
                "y": 0.03371757925072046, 
                "x": 314.0
            }, 
            {
                "y": 0.03021699452443723, 
                "x": 315.0
            }, 
            {
                "y": 0.03478756772169946, 
                "x": 316.0
            }, 
            {
                "y": 0.04750137287204833, 
                "x": 317.0
            }, 
            {
                "y": 0.03761242845461979, 
                "x": 318.0
            }, 
            {
                "y": 0.05021398002853066, 
                "x": 319.0
            }, 
            {
                "y": 0.05057675244010648, 
                "x": 320.0
            }, 
            {
                "y": 0.034060779114827654, 
                "x": 321.0
            }, 
            {
                "y": 0.04580589750930432, 
                "x": 322.0
            }, 
            {
                "y": 0.03590926857560742, 
                "x": 323.0
            }, 
            {
                "y": 0.04264332109573567, 
                "x": 324.0
            }, 
            {
                "y": 0.04639463387367245, 
                "x": 325.0
            }, 
            {
                "y": 0.039887640449438204, 
                "x": 326.0
            }, 
            {
                "y": 0.03539309544531477, 
                "x": 327.0
            }, 
            {
                "y": 0.039720763035857906, 
                "x": 328.0
            }, 
            {
                "y": 0.043478260869565216, 
                "x": 329.0
            }, 
            {
                "y": 0.05424854691392195, 
                "x": 330.0
            }, 
            {
                "y": 0.056853976945987, 
                "x": 331.0
            }, 
            {
                "y": 0.0529549444119368, 
                "x": 332.0
            }, 
            {
                "y": 0.04009575104727708, 
                "x": 333.0
            }, 
            {
                "y": 0.04879401164402551, 
                "x": 334.0
            }, 
            {
                "y": 0.03891895906639062, 
                "x": 335.0
            }, 
            {
                "y": 0.07856125081834635, 
                "x": 336.0
            }, 
            {
                "y": 0.10476457732765292, 
                "x": 337.0
            }, 
            {
                "y": 0.050672774119667925, 
                "x": 338.0
            }, 
            {
                "y": 0.06971935007385524, 
                "x": 339.0
            }, 
            {
                "y": 0.056414922656960874, 
                "x": 340.0
            }, 
            {
                "y": 0.09371507841701672, 
                "x": 341.0
            }, 
            {
                "y": 0.08582326764144946, 
                "x": 342.0
            }, 
            {
                "y": 0.06052209100305689, 
                "x": 343.0
            }, 
            {
                "y": 0.07453769559032716, 
                "x": 344.0
            }, 
            {
                "y": 0.05068870523415978, 
                "x": 345.0
            }, 
            {
                "y": 0.05521844660194174, 
                "x": 346.0
            }, 
            {
                "y": 0.0542972385975799, 
                "x": 347.0
            }, 
            {
                "y": 0.07586067894539834, 
                "x": 348.0
            }, 
            {
                "y": 0.09247381112770796, 
                "x": 349.0
            }, 
            {
                "y": 0.0750508894592442, 
                "x": 350.0
            }, 
            {
                "y": 0.05344500947252966, 
                "x": 351.0
            }, 
            {
                "y": 0.07652897854626961, 
                "x": 352.0
            }, 
            {
                "y": 0.07308877065247829, 
                "x": 353.0
            }, 
            {
                "y": 0.09921931233043574, 
                "x": 354.0
            }, 
            {
                "y": 0.15120008961212208, 
                "x": 355.0
            }, 
            {
                "y": 0.21467327680107498, 
                "x": 356.0
            }, 
            {
                "y": 0.20210461455515225, 
                "x": 357.0
            }, 
            {
                "y": 0.12617144632954908, 
                "x": 358.0
            }, 
            {
                "y": 0.12772404148700617, 
                "x": 359.0
            }, 
            {
                "y": 0.1808676472147697, 
                "x": 360.0
            }, 
            {
                "y": 0.1543882274370725, 
                "x": 361.0
            }, 
            {
                "y": 0.152120396308558, 
                "x": 362.0
            }, 
            {
                "y": 0.11602204254004224, 
                "x": 363.0
            }, 
            {
                "y": 0.09189018617860524, 
                "x": 364.0
            }, 
            {
                "y": 0.12884775969160728, 
                "x": 365.0
            }, 
            {
                "y": 0.13595594020456334, 
                "x": 366.0
            }, 
            {
                "y": 0.13966888841109437, 
                "x": 367.0
            }, 
            {
                "y": 0.30341890921694353, 
                "x": 368.0
            }, 
            {
                "y": 0.2691792484958565, 
                "x": 369.0
            }, 
            {
                "y": 0.25223468226881196, 
                "x": 370.0
            }, 
            {
                "y": 0.25582563839171063, 
                "x": 371.0
            }, 
            {
                "y": 0.3447374528221226, 
                "x": 372.0
            }, 
            {
                "y": 0.3582728732673493, 
                "x": 373.0
            }, 
            {
                "y": 0.35248767368892875, 
                "x": 374.0
            }, 
            {
                "y": 0.3296910420009679, 
                "x": 375.0
            }, 
            {
                "y": 0.22898032200357787, 
                "x": 376.0
            }, 
            {
                "y": 0.25997227783767135, 
                "x": 377.0
            }, 
            {
                "y": 0.2613942991708777, 
                "x": 378.0
            }, 
            {
                "y": 0.31497442636467876, 
                "x": 379.0
            }, 
            {
                "y": 0.36727210501870095, 
                "x": 380.0
            }, 
            {
                "y": 0.4782868210444252, 
                "x": 381.0
            }, 
            {
                "y": 0.42313598362054256, 
                "x": 382.0
            }, 
            {
                "y": 0.11262357897410928, 
                "x": 383.0
            }, 
            {
                "y": 0.1254659216879571, 
                "x": 384.0
            }, 
            {
                "y": 0.17147599744999217, 
                "x": 385.0
            }, 
            {
                "y": 0.1963068533895154, 
                "x": 386.0
            }, 
            {
                "y": 0.16468632340716838, 
                "x": 387.0
            }, 
            {
                "y": 0.13578938974516705, 
                "x": 388.0
            }, 
            {
                "y": 0.08201260200118184, 
                "x": 389.0
            }, 
            {
                "y": 0.5071830391273092, 
                "x": 390.0
            }, 
            {
                "y": 0.37003424048908207, 
                "x": 391.0
            }, 
            {
                "y": 0.7204783894788364, 
                "x": 392.0
            }, 
            {
                "y": 0.7410291537481674, 
                "x": 393.0
            }, 
            {
                "y": 0.44933740285321444, 
                "x": 394.0
            }, 
            {
                "y": 0.313669040091167, 
                "x": 395.0
            }, 
            {
                "y": 0.34470563986852243, 
                "x": 396.0
            }, 
            {
                "y": 0.6885267023126972, 
                "x": 397.0
            }, 
            {
                "y": 0.7254990121942911, 
                "x": 398.0
            }, 
            {
                "y": 0.8861213130170673, 
                "x": 399.0
            }, 
            {
                "y": 0.6732848003529671, 
                "x": 400.0
            }, 
            {
                "y": 0.757840836355878, 
                "x": 401.0
            }, 
            {
                "y": 0.3554382492026834, 
                "x": 402.0
            }, 
            {
                "y": 0.48749873468974586, 
                "x": 403.0
            }, 
            {
                "y": 0.5901344817564532, 
                "x": 404.0
            }, 
            {
                "y": 0.34774950903983154, 
                "x": 405.0
            }, 
            {
                "y": 0.35101223924255254, 
                "x": 406.0
            }, 
            {
                "y": 0.36354982150685783, 
                "x": 407.0
            }, 
            {
                "y": 0.3021749617662455, 
                "x": 408.0
            }, 
            {
                "y": 0.16684000218950135, 
                "x": 409.0
            }, 
            {
                "y": 0.13161058261157652, 
                "x": 410.0
            }, 
            {
                "y": 0.0824944511163788, 
                "x": 411.0
            }, 
            {
                "y": 0.03265338160696239, 
                "x": 412.0
            }, 
            {
                "y": 0.1529247166459686, 
                "x": 413.0
            }, 
            {
                "y": 0.4081695568400771, 
                "x": 414.0
            }, 
            {
                "y": 0.46574764557715925, 
                "x": 415.0
            }, 
            {
                "y": 0.39172963158203017, 
                "x": 416.0
            }, 
            {
                "y": 0.3999999999999999, 
                "x": 417.0
            }, 
            {
                "y": 0.34618383435848565, 
                "x": 418.0
            }, 
            {
                "y": 0.24838508814875732, 
                "x": 419.0
            }, 
            {
                "y": 0.09212174007731257, 
                "x": 420.0
            }, 
            {
                "y": 0.3774234707108848, 
                "x": 421.0
            }, 
            {
                "y": 0.8493058454412022, 
                "x": 422.0
            }, 
            {
                "y": 0.9134978765310519, 
                "x": 423.0
            }, 
            {
                "y": 0.9097114659721746, 
                "x": 424.0
            }, 
            {
                "y": 0.6554402364423673, 
                "x": 425.0
            }, 
            {
                "y": 0.3062469983249189, 
                "x": 426.0
            }, 
            {
                "y": 0.46625573770491807, 
                "x": 427.0
            }, 
            {
                "y": 0.4149666441071256, 
                "x": 428.0
            }, 
            {
                "y": 0.2884576359888496, 
                "x": 429.0
            }, 
            {
                "y": 0.12014698833679502, 
                "x": 430.0
            }, 
            {
                "y": 0.14165440628422918, 
                "x": 431.0
            }, 
            {
                "y": 0.13157937847091394, 
                "x": 432.0
            }, 
            {
                "y": 0.1613041613041613, 
                "x": 433.0
            }, 
            {
                "y": 0.22285256561277858, 
                "x": 434.0
            }, 
            {
                "y": 0.1200704494984302, 
                "x": 435.0
            }, 
            {
                "y": 0.16940019851585766, 
                "x": 436.0
            }, 
            {
                "y": 0.20839613581872182, 
                "x": 437.0
            }, 
            {
                "y": 0.12311264826995832, 
                "x": 438.0
            }, 
            {
                "y": 0.0055147058823529415, 
                "x": 439.0
            }, 
            {
                "y": 0.1023076607779645, 
                "x": 440.0
            }, 
            {
                "y": 0.049040774092510765, 
                "x": 441.0
            }, 
            {
                "y": 0.07498323156125053, 
                "x": 442.0
            }, 
            {
                "y": 0.07562857010885463, 
                "x": 443.0
            }, 
            {
                "y": 0.12755546538411044, 
                "x": 444.0
            }, 
            {
                "y": 0.12516103573542553, 
                "x": 445.0
            }, 
            {
                "y": 0.1621660280970626, 
                "x": 446.0
            }, 
            {
                "y": 0.15407095926412614, 
                "x": 447.0
            }, 
            {
                "y": 0.2534252552578759, 
                "x": 448.0
            }, 
            {
                "y": 0.3227897211191747, 
                "x": 449.0
            }, 
            {
                "y": 0.268328568523547, 
                "x": 450.0
            }, 
            {
                "y": 0.19237364881789634, 
                "x": 451.0
            }, 
            {
                "y": 0.18837572945516978, 
                "x": 452.0
            }, 
            {
                "y": 0.27752102518457655, 
                "x": 453.0
            }, 
            {
                "y": 0.3010207263580234, 
                "x": 454.0
            }, 
            {
                "y": 0.3629785361560651, 
                "x": 455.0
            }, 
            {
                "y": 0.4196502095547115, 
                "x": 456.0
            }, 
            {
                "y": 0.5419784752888913, 
                "x": 457.0
            }, 
            {
                "y": 0.47458382546297334, 
                "x": 458.0
            }, 
            {
                "y": 0.3646903332019385, 
                "x": 459.0
            }, 
            {
                "y": 0.3285978999382335, 
                "x": 460.0
            }, 
            {
                "y": 0.2721551284232013, 
                "x": 461.0
            }, 
            {
                "y": 0.3493972793681113, 
                "x": 462.0
            }, 
            {
                "y": 0.35939774088432663, 
                "x": 463.0
            }, 
            {
                "y": 0.5093324172678346, 
                "x": 464.0
            }, 
            {
                "y": 0.5473874813097573, 
                "x": 465.0
            }, 
            {
                "y": 0.6516677920324105, 
                "x": 466.0
            }, 
            {
                "y": 0.543629952905787, 
                "x": 467.0
            }, 
            {
                "y": 0.35945647327918745, 
                "x": 468.0
            }, 
            {
                "y": 0.24680272669234096, 
                "x": 469.0
            }, 
            {
                "y": 0.3919396428230351, 
                "x": 470.0
            }, 
            {
                "y": 0.283627569528416, 
                "x": 471.0
            }, 
            {
                "y": 0.29730859038957846, 
                "x": 472.0
            }, 
            {
                "y": 0.5697523985192585, 
                "x": 473.0
            }, 
            {
                "y": 0.6131741761018316, 
                "x": 474.0
            }, 
            {
                "y": 0.2698852303940005, 
                "x": 475.0
            }, 
            {
                "y": 0.43896873117011326, 
                "x": 476.0
            }, 
            {
                "y": 0.41671279820746016, 
                "x": 477.0
            }, 
            {
                "y": 0.3849501935156399, 
                "x": 478.0
            }, 
            {
                "y": 0.339694913623021, 
                "x": 479.0
            }, 
            {
                "y": 0.35144969167719936, 
                "x": 480.0
            }, 
            {
                "y": 0.30422904600590095, 
                "x": 481.0
            }, 
            {
                "y": 0.2759014711801903, 
                "x": 482.0
            }, 
            {
                "y": 0.47523267492467364, 
                "x": 483.0
            }, 
            {
                "y": 0.4940152339499456, 
                "x": 484.0
            }, 
            {
                "y": 0.4024246413779864, 
                "x": 485.0
            }, 
            {
                "y": 0.4181879420680364, 
                "x": 486.0
            }, 
            {
                "y": 0.2973595739054886, 
                "x": 487.0
            }, 
            {
                "y": 0.27154440882519326, 
                "x": 488.0
            }, 
            {
                "y": 0.21309623583427467, 
                "x": 489.0
            }, 
            {
                "y": 0.28268724856946903, 
                "x": 490.0
            }, 
            {
                "y": 0.25207535531625075, 
                "x": 491.0
            }, 
            {
                "y": 0.23057528636334546, 
                "x": 492.0
            }, 
            {
                "y": 0.19419798624264778, 
                "x": 493.0
            }, 
            {
                "y": 0.19548658993955484, 
                "x": 494.0
            }, 
            {
                "y": 0.23077330228126824, 
                "x": 495.0
            }, 
            {
                "y": 0.2653288448187784, 
                "x": 496.0
            }, 
            {
                "y": 0.2565779838906517, 
                "x": 497.0
            }, 
            {
                "y": 0.28725832871164536, 
                "x": 498.0
            }, 
            {
                "y": 0.27889698528361195, 
                "x": 499.0
            }, 
            {
                "y": 0.18681547801557613, 
                "x": 500.0
            }, 
            {
                "y": 0.14445775983432035, 
                "x": 501.0
            }, 
            {
                "y": 0.20683628887175534, 
                "x": 502.0
            }, 
            {
                "y": 0.1598394774478622, 
                "x": 503.0
            }, 
            {
                "y": 0.22490245669331368, 
                "x": 504.0
            }, 
            {
                "y": 0.23398999643607674, 
                "x": 505.0
            }, 
            {
                "y": 0.19353056149650535, 
                "x": 506.0
            }, 
            {
                "y": 0.19681338702377776, 
                "x": 507.0
            }, 
            {
                "y": 0.20090660981809239, 
                "x": 508.0
            }, 
            {
                "y": 0.2781849368470295, 
                "x": 509.0
            }, 
            {
                "y": 0.2234799718220905, 
                "x": 510.0
            }, 
            {
                "y": 0.22526995939609545, 
                "x": 511.0
            }, 
            {
                "y": 0.22926617455492831, 
                "x": 512.0
            }, 
            {
                "y": 0.21589355805525248, 
                "x": 513.0
            }, 
            {
                "y": 0.25619782363597204, 
                "x": 514.0
            }, 
            {
                "y": 0.2384677494076692, 
                "x": 515.0
            }, 
            {
                "y": 0.3006717309779249, 
                "x": 516.0
            }, 
            {
                "y": 0.2618185228165184, 
                "x": 517.0
            }, 
            {
                "y": 0.2373757455268389, 
                "x": 518.0
            }, 
            {
                "y": 0.1824696157178652, 
                "x": 519.0
            }, 
            {
                "y": 0.2373702885452232, 
                "x": 520.0
            }, 
            {
                "y": 0.25875899720587664, 
                "x": 521.0
            }, 
            {
                "y": 0.27486200058105015, 
                "x": 522.0
            }, 
            {
                "y": 0.31303972366148536, 
                "x": 523.0
            }, 
            {
                "y": 0.25763831544178367, 
                "x": 524.0
            }, 
            {
                "y": 0.2398202387292021, 
                "x": 525.0
            }, 
            {
                "y": 0.26547056722105344, 
                "x": 526.0
            }, 
            {
                "y": 0.249183519256138, 
                "x": 527.0
            }, 
            {
                "y": 0.21846029826682792, 
                "x": 528.0
            }, 
            {
                "y": 0.1827473375899214, 
                "x": 529.0
            }, 
            {
                "y": 0.12481536189069423, 
                "x": 530.0
            }, 
            {
                "y": 0.14496314496314497, 
                "x": 531.0
            }, 
            {
                "y": 0.19306974342179847, 
                "x": 532.0
            }, 
            {
                "y": 0.17494973722267293, 
                "x": 533.0
            }, 
            {
                "y": 0.25954542442515405, 
                "x": 534.0
            }, 
            {
                "y": 0.3066971680997081, 
                "x": 535.0
            }, 
            {
                "y": 0.28828828828828823, 
                "x": 536.0
            }, 
            {
                "y": 0.3441997660580786, 
                "x": 537.0
            }, 
            {
                "y": 0.44610602139052086, 
                "x": 538.0
            }, 
            {
                "y": 0.3136717566303474, 
                "x": 539.0
            }, 
            {
                "y": 0.290672619124421, 
                "x": 540.0
            }, 
            {
                "y": 0.17178763155838797, 
                "x": 541.0
            }, 
            {
                "y": 0.1163523703998537, 
                "x": 542.0
            }, 
            {
                "y": 0.11831306898767169, 
                "x": 543.0
            }, 
            {
                "y": 0.16540730364787815, 
                "x": 544.0
            }, 
            {
                "y": 0.16128494523489673, 
                "x": 545.0
            }, 
            {
                "y": 0.12256612500258099, 
                "x": 546.0
            }, 
            {
                "y": 0.13741721854304637, 
                "x": 547.0
            }, 
            {
                "y": 0.0862257346357012, 
                "x": 548.0
            }, 
            {
                "y": 0.10989365130518852, 
                "x": 549.0
            }, 
            {
                "y": 0.09432734344493869, 
                "x": 550.0
            }, 
            {
                "y": 0.12014864147483229, 
                "x": 551.0
            }, 
            {
                "y": 0.0860922734852696, 
                "x": 552.0
            }, 
            {
                "y": 0.12182822702159718, 
                "x": 553.0
            }, 
            {
                "y": 0.14868646368458424, 
                "x": 554.0
            }, 
            {
                "y": 0.15735233496260526, 
                "x": 555.0
            }, 
            {
                "y": 0.10062674849818916, 
                "x": 556.0
            }, 
            {
                "y": 0.12852483771851636, 
                "x": 557.0
            }, 
            {
                "y": 0.1459528693859275, 
                "x": 558.0
            }, 
            {
                "y": 0.09528552119432109, 
                "x": 559.0
            }, 
            {
                "y": 0.10683895367160415, 
                "x": 560.0
            }, 
            {
                "y": 0.1212795170606057, 
                "x": 561.0
            }, 
            {
                "y": 0.20481281510351484, 
                "x": 562.0
            }, 
            {
                "y": 0.19568373649629645, 
                "x": 563.0
            }, 
            {
                "y": 0.16523557518195306, 
                "x": 564.0
            }, 
            {
                "y": 0.19431431383943923, 
                "x": 565.0
            }, 
            {
                "y": 0.1622976327635971, 
                "x": 566.0
            }, 
            {
                "y": 0.1876932118718778, 
                "x": 567.0
            }, 
            {
                "y": 0.22005138835445548, 
                "x": 568.0
            }, 
            {
                "y": 0.15764235545991764, 
                "x": 569.0
            }, 
            {
                "y": 0.18039195903851485, 
                "x": 570.0
            }, 
            {
                "y": 0.1790185000553894, 
                "x": 571.0
            }, 
            {
                "y": 0.17233322087691022, 
                "x": 572.0
            }, 
            {
                "y": 0.16679787208664326, 
                "x": 573.0
            }, 
            {
                "y": 0.18188995026446675, 
                "x": 574.0
            }, 
            {
                "y": 0.18824652467036573, 
                "x": 575.0
            }, 
            {
                "y": 0.19163642425719088, 
                "x": 576.0
            }, 
            {
                "y": 0.19399380351784534, 
                "x": 577.0
            }, 
            {
                "y": 0.19576997028491522, 
                "x": 578.0
            }, 
            {
                "y": 0.1847915370255134, 
                "x": 579.0
            }, 
            {
                "y": 0.1859180616166221, 
                "x": 580.0
            }, 
            {
                "y": 0.15879080608922366, 
                "x": 581.0
            }, 
            {
                "y": 0.14308036250871414, 
                "x": 582.0
            }, 
            {
                "y": 0.15014384669523023, 
                "x": 583.0
            }, 
            {
                "y": 0.15488758724702745, 
                "x": 584.0
            }, 
            {
                "y": 0.16150154835354466, 
                "x": 585.0
            }, 
            {
                "y": 0.12587815935492058, 
                "x": 586.0
            }, 
            {
                "y": 0.12365256500944918, 
                "x": 587.0
            }, 
            {
                "y": 0.18236757909704943, 
                "x": 588.0
            }, 
            {
                "y": 0.16865484668254205, 
                "x": 589.0
            }, 
            {
                "y": 0.1486702470888388, 
                "x": 590.0
            }, 
            {
                "y": 0.20166172508257896, 
                "x": 591.0
            }, 
            {
                "y": 0.15397828988896595, 
                "x": 592.0
            }, 
            {
                "y": 0.1987491010525857, 
                "x": 593.0
            }, 
            {
                "y": 0.19359442734350865, 
                "x": 594.0
            }, 
            {
                "y": 0.16311292985856846, 
                "x": 595.0
            }, 
            {
                "y": 0.15758410753849306, 
                "x": 596.0
            }, 
            {
                "y": 0.1602955909521227, 
                "x": 597.0
            }, 
            {
                "y": 0.18429778043661219, 
                "x": 598.0
            }, 
            {
                "y": 0.16574189695423205, 
                "x": 599.0
            }, 
            {
                "y": 0.17127213133389538, 
                "x": 600.0
            }, 
            {
                "y": 0.19595579732732707, 
                "x": 601.0
            }, 
            {
                "y": 0.16780776760084795, 
                "x": 602.0
            }, 
            {
                "y": 0.17852119939242783, 
                "x": 603.0
            }, 
            {
                "y": 0.22889653892931497, 
                "x": 604.0
            }, 
            {
                "y": 0.2531190570729975, 
                "x": 605.0
            }, 
            {
                "y": 0.27392735824405545, 
                "x": 606.0
            }, 
            {
                "y": 0.35244291140898576, 
                "x": 607.0
            }, 
            {
                "y": 0.3085394055819985, 
                "x": 608.0
            }, 
            {
                "y": 0.3158038023503789, 
                "x": 609.0
            }, 
            {
                "y": 0.26921714488133186, 
                "x": 610.0
            }, 
            {
                "y": 0.4032295509066989, 
                "x": 611.0
            }, 
            {
                "y": 0.3866646673664217, 
                "x": 612.0
            }, 
            {
                "y": 0.25145292522278184, 
                "x": 613.0
            }, 
            {
                "y": 0.35024315460108824, 
                "x": 614.0
            }, 
            {
                "y": 0.3790116113682795, 
                "x": 615.0
            }, 
            {
                "y": 0.3940478042204594, 
                "x": 616.0
            }, 
            {
                "y": 0.4122127697452918, 
                "x": 617.0
            }, 
            {
                "y": 0.37215013518778695, 
                "x": 618.0
            }, 
            {
                "y": 0.3761415461156618, 
                "x": 619.0
            }, 
            {
                "y": 0.3013555787278415, 
                "x": 620.0
            }, 
            {
                "y": 0.270191558771405, 
                "x": 621.0
            }, 
            {
                "y": 0.1504170936843371, 
                "x": 622.0
            }, 
            {
                "y": 0.09936906291021497, 
                "x": 623.0
            }, 
            {
                "y": 0.1801504368274337, 
                "x": 624.0
            }, 
            {
                "y": 0.16490351872871736, 
                "x": 625.0
            }, 
            {
                "y": 0.22611163670766316, 
                "x": 626.0
            }, 
            {
                "y": 0.24811803673592292, 
                "x": 627.0
            }, 
            {
                "y": 0.21037591673222827, 
                "x": 628.0
            }, 
            {
                "y": 0.3270873988745951, 
                "x": 629.0
            }, 
            {
                "y": 0.3668189663925272, 
                "x": 630.0
            }, 
            {
                "y": 0.29445466856488073, 
                "x": 631.0
            }, 
            {
                "y": 0.3855275159622986, 
                "x": 632.0
            }, 
            {
                "y": 0.3461857521108195, 
                "x": 633.0
            }, 
            {
                "y": 0.424776916563538, 
                "x": 634.0
            }, 
            {
                "y": 0.4270679016321641, 
                "x": 635.0
            }, 
            {
                "y": 0.23142303295392416, 
                "x": 636.0
            }, 
            {
                "y": 0.2983747128413656, 
                "x": 637.0
            }, 
            {
                "y": 0.49817081194894064, 
                "x": 638.0
            }, 
            {
                "y": 0.5403735125904643, 
                "x": 639.0
            }, 
            {
                "y": 0.520773022455207, 
                "x": 640.0
            }, 
            {
                "y": 0.5058953945379421, 
                "x": 641.0
            }, 
            {
                "y": 0.509660677169809, 
                "x": 642.0
            }, 
            {
                "y": 0.5450757252689679, 
                "x": 643.0
            }, 
            {
                "y": 0.22711432214194643, 
                "x": 644.0
            }, 
            {
                "y": 0.2113104843985798, 
                "x": 645.0
            }, 
            {
                "y": 0.22489198179941114, 
                "x": 646.0
            }, 
            {
                "y": 0.622748792615326, 
                "x": 647.0
            }, 
            {
                "y": 0.597168345182883, 
                "x": 648.0
            }, 
            {
                "y": 0.623796127751117, 
                "x": 649.0
            }, 
            {
                "y": 0.6203334292182048, 
                "x": 650.0
            }, 
            {
                "y": 0.7030593881223757, 
                "x": 651.0
            }, 
            {
                "y": 0.5075538957732133, 
                "x": 652.0
            }, 
            {
                "y": 0.7747092183836355, 
                "x": 653.0
            }, 
            {
                "y": 0.7251489755703805, 
                "x": 654.0
            }, 
            {
                "y": 0.8221025303212307, 
                "x": 655.0
            }, 
            {
                "y": 0.8405800878210222, 
                "x": 656.0
            }, 
            {
                "y": 0.9873919134341338, 
                "x": 657.0
            }, 
            {
                "y": 0.9938998835855646, 
                "x": 658.0
            }, 
            {
                "y": 0.9674112320874025, 
                "x": 659.0
            }, 
            {
                "y": 0.9054770132998219, 
                "x": 660.0
            }, 
            {
                "y": 0.7230366152047291, 
                "x": 661.0
            }, 
            {
                "y": 0.7989166564077311, 
                "x": 662.0
            }, 
            {
                "y": 0.9582697906557605, 
                "x": 663.0
            }, 
            {
                "y": 0.6009798007252383, 
                "x": 664.0
            }, 
            {
                "y": 0.47512152010605385, 
                "x": 665.0
            }, 
            {
                "y": 0.41574549231794866, 
                "x": 666.0
            }, 
            {
                "y": 0.5502478741915362, 
                "x": 667.0
            }, 
            {
                "y": 0.5574229089109337, 
                "x": 668.0
            }, 
            {
                "y": 0.6391564432728378, 
                "x": 669.0
            }, 
            {
                "y": 0.6157196022885075, 
                "x": 670.0
            }, 
            {
                "y": 0.8172283773935637, 
                "x": 671.0
            }, 
            {
                "y": 0.6503202151652938, 
                "x": 672.0
            }, 
            {
                "y": 0.6251661262027536, 
                "x": 673.0
            }, 
            {
                "y": 0.5806009889691898, 
                "x": 674.0
            }, 
            {
                "y": 0.4508776148112526, 
                "x": 675.0
            }, 
            {
                "y": 0.470896537821902, 
                "x": 676.0
            }, 
            {
                "y": 0.30557567979687167, 
                "x": 677.0
            }, 
            {
                "y": 0.18472965728359764, 
                "x": 678.0
            }, 
            {
                "y": 0.06062891325093683, 
                "x": 679.0
            }, 
            {
                "y": 0.05754254207930611, 
                "x": 680.0
            }, 
            {
                "y": 0.3152503669874409, 
                "x": 681.0
            }, 
            {
                "y": 0.34331084536885953, 
                "x": 682.0
            }, 
            {
                "y": 0.35704871320096265, 
                "x": 683.0
            }, 
            {
                "y": 0.18694194576293685, 
                "x": 684.0
            }, 
            {
                "y": 0.2545066413662239, 
                "x": 685.0
            }, 
            {
                "y": 0.22701142395851173, 
                "x": 686.0
            }, 
            {
                "y": 0.3423315727198429, 
                "x": 687.0
            }, 
            {
                "y": 0.2615763489842874, 
                "x": 688.0
            }, 
            {
                "y": 0.16964197652628463, 
                "x": 689.0
            }, 
            {
                "y": 0.2394263743115452, 
                "x": 690.0
            }, 
            {
                "y": 0.17389182010695955, 
                "x": 691.0
            }, 
            {
                "y": 0.14513243733914996, 
                "x": 692.0
            }, 
            {
                "y": 0.023315467457156826, 
                "x": 693.0
            }, 
            {
                "y": 0.11798283783910238, 
                "x": 694.0
            }, 
            {
                "y": 0.13918940739544647, 
                "x": 695.0
            }, 
            {
                "y": 0.1481221069900978, 
                "x": 696.0
            }, 
            {
                "y": 0.1225131605934231, 
                "x": 697.0
            }, 
            {
                "y": 0.16450807763469968, 
                "x": 698.0
            }, 
            {
                "y": 0.2200135371023476, 
                "x": 699.0
            }, 
            {
                "y": 0.256394809450944, 
                "x": 700.0
            }, 
            {
                "y": 0.3732724736908837, 
                "x": 701.0
            }, 
            {
                "y": 0.33365664403491757, 
                "x": 702.0
            }, 
            {
                "y": 0.32465073435341074, 
                "x": 703.0
            }, 
            {
                "y": 0.2968185852004036, 
                "x": 704.0
            }, 
            {
                "y": 0.2234190325332033, 
                "x": 705.0
            }, 
            {
                "y": 0.33576471506026445, 
                "x": 706.0
            }, 
            {
                "y": 0.4560331056689684, 
                "x": 707.0
            }, 
            {
                "y": 0.3919843478472214, 
                "x": 708.0
            }, 
            {
                "y": 0.2281202929413598, 
                "x": 709.0
            }, 
            {
                "y": 0.2721832147401159, 
                "x": 710.0
            }, 
            {
                "y": 0.23900414937759337, 
                "x": 711.0
            }, 
            {
                "y": 0.1931077083902543, 
                "x": 712.0
            }, 
            {
                "y": 0.32516976784094537, 
                "x": 713.0
            }, 
            {
                "y": 0.38093865244393194, 
                "x": 714.0
            }, 
            {
                "y": 0.30427954456223005, 
                "x": 715.0
            }, 
            {
                "y": 0.22874511017927, 
                "x": 716.0
            }, 
            {
                "y": 0.2336400094361878, 
                "x": 717.0
            }, 
            {
                "y": 0.23465475525777033, 
                "x": 718.0
            }, 
            {
                "y": 0.21025119790910407, 
                "x": 719.0
            }, 
            {
                "y": 0.2776041334438987, 
                "x": 720.0
            }, 
            {
                "y": 0.2878168438266558, 
                "x": 721.0
            }, 
            {
                "y": 0.205138966121434, 
                "x": 722.0
            }, 
            {
                "y": 0.1552074236956453, 
                "x": 723.0
            }, 
            {
                "y": 0.23407534679232894, 
                "x": 724.0
            }, 
            {
                "y": 0.22396701576676886, 
                "x": 725.0
            }, 
            {
                "y": 0.23201903122943765, 
                "x": 726.0
            }, 
            {
                "y": 0.24180044935922382, 
                "x": 727.0
            }, 
            {
                "y": 0.2451144063635471, 
                "x": 728.0
            }, 
            {
                "y": 0.23740713527634905, 
                "x": 729.0
            }, 
            {
                "y": 0.16006476609032558, 
                "x": 730.0
            }, 
            {
                "y": 0.18763384830334753, 
                "x": 731.0
            }, 
            {
                "y": 0.20447775535697124, 
                "x": 732.0
            }, 
            {
                "y": 0.21382506559427186, 
                "x": 733.0
            }, 
            {
                "y": 0.24523629538878605, 
                "x": 734.0
            }, 
            {
                "y": 0.24316109422492407, 
                "x": 735.0
            }, 
            {
                "y": 0.20558215156715742, 
                "x": 736.0
            }, 
            {
                "y": 0.1978802082689192, 
                "x": 737.0
            }, 
            {
                "y": 0.2531911352375587, 
                "x": 738.0
            }, 
            {
                "y": 0.23963931837285718, 
                "x": 739.0
            }, 
            {
                "y": 0.2104239695008059, 
                "x": 740.0
            }, 
            {
                "y": 0.17674926318087547, 
                "x": 741.0
            }, 
            {
                "y": 0.18111043831790716, 
                "x": 742.0
            }, 
            {
                "y": 0.1913103662247467, 
                "x": 743.0
            }, 
            {
                "y": 0.19955023399987845, 
                "x": 744.0
            }, 
            {
                "y": 0.22144230173001797, 
                "x": 745.0
            }, 
            {
                "y": 0.20474126943665563, 
                "x": 746.0
            }, 
            {
                "y": 0.2227549865524334, 
                "x": 747.0
            }, 
            {
                "y": 0.2283726305505582, 
                "x": 748.0
            }, 
            {
                "y": 0.22139964723126226, 
                "x": 749.0
            }, 
            {
                "y": 0.20987481374883793, 
                "x": 750.0
            }, 
            {
                "y": 0.2516653947147163, 
                "x": 751.0
            }, 
            {
                "y": 0.20576651918121258, 
                "x": 752.0
            }, 
            {
                "y": 0.2152038472763263, 
                "x": 753.0
            }, 
            {
                "y": 0.16908654793218922, 
                "x": 754.0
            }, 
            {
                "y": 0.1288609004840852, 
                "x": 755.0
            }, 
            {
                "y": 0.16777364182663065, 
                "x": 756.0
            }, 
            {
                "y": 0.16779672946531218, 
                "x": 757.0
            }, 
            {
                "y": 0.17157313128516233, 
                "x": 758.0
            }, 
            {
                "y": 0.17983549815772823, 
                "x": 759.0
            }, 
            {
                "y": 0.19095386910503231, 
                "x": 760.0
            }, 
            {
                "y": 0.1657095980311731, 
                "x": 761.0
            }, 
            {
                "y": 0.19809048361934473, 
                "x": 762.0
            }, 
            {
                "y": 0.16331476777516254, 
                "x": 763.0
            }, 
            {
                "y": 0.1621992428669428, 
                "x": 764.0
            }, 
            {
                "y": 0.1860395929144302, 
                "x": 765.0
            }, 
            {
                "y": 0.17686031742399105, 
                "x": 766.0
            }, 
            {
                "y": 0.1321675855283919, 
                "x": 767.0
            }, 
            {
                "y": 0.19880669097047207, 
                "x": 768.0
            }, 
            {
                "y": 0.19857783841935397, 
                "x": 769.0
            }, 
            {
                "y": 0.23497554371028143, 
                "x": 770.0
            }, 
            {
                "y": 0.2015378389316066, 
                "x": 771.0
            }, 
            {
                "y": 0.23225169996124442, 
                "x": 772.0
            }, 
            {
                "y": 0.17815186677087716, 
                "x": 773.0
            }, 
            {
                "y": 0.15670003618381378, 
                "x": 774.0
            }, 
            {
                "y": 0.20775901414879056, 
                "x": 775.0
            }, 
            {
                "y": 0.22444174576817266, 
                "x": 776.0
            }, 
            {
                "y": 0.18290534792038635, 
                "x": 777.0
            }, 
            {
                "y": 0.16136030489592493, 
                "x": 778.0
            }, 
            {
                "y": 0.1597535125618246, 
                "x": 779.0
            }, 
            {
                "y": 0.21939313185149292, 
                "x": 780.0
            }, 
            {
                "y": 0.20780736957314852, 
                "x": 781.0
            }, 
            {
                "y": 0.2061825816260045, 
                "x": 782.0
            }, 
            {
                "y": 0.18412570507655115, 
                "x": 783.0
            }, 
            {
                "y": 0.24939554503832506, 
                "x": 784.0
            }, 
            {
                "y": 0.19248120300751875, 
                "x": 785.0
            }, 
            {
                "y": 0.1646128709218363, 
                "x": 786.0
            }, 
            {
                "y": 0.27250320418022284, 
                "x": 787.0
            }, 
            {
                "y": 0.3824872941032393, 
                "x": 788.0
            }, 
            {
                "y": 0.3006784790354859, 
                "x": 789.0
            }, 
            {
                "y": 0.2522477729438575, 
                "x": 790.0
            }, 
            {
                "y": 0.21615821688979928, 
                "x": 791.0
            }, 
            {
                "y": 0.21565578019699325, 
                "x": 792.0
            }, 
            {
                "y": 0.14707143995195668, 
                "x": 793.0
            }, 
            {
                "y": 0.2566410356354016, 
                "x": 794.0
            }, 
            {
                "y": 0.3196474476680133, 
                "x": 795.0
            }, 
            {
                "y": 0.26189389096886134, 
                "x": 796.0
            }, 
            {
                "y": 0.13782136231115824, 
                "x": 797.0
            }, 
            {
                "y": 0.18838147248177556, 
                "x": 798.0
            }, 
            {
                "y": 0.22639422956093389, 
                "x": 799.0
            }, 
            {
                "y": 0.18376707422812547, 
                "x": 800.0
            }, 
            {
                "y": 0.20627312372064635, 
                "x": 801.0
            }, 
            {
                "y": 0.2291041604965297, 
                "x": 802.0
            }, 
            {
                "y": 0.22101549803797219, 
                "x": 803.0
            }, 
            {
                "y": 0.11688539752039993, 
                "x": 804.0
            }, 
            {
                "y": 0.08595709632735576, 
                "x": 805.0
            }, 
            {
                "y": 0.18624544349939245, 
                "x": 806.0
            }, 
            {
                "y": 0.1843957569148409, 
                "x": 807.0
            }, 
            {
                "y": 0.17141777525867152, 
                "x": 808.0
            }, 
            {
                "y": 0.16508995591564396, 
                "x": 809.0
            }, 
            {
                "y": 0.1488891068179094, 
                "x": 810.0
            }, 
            {
                "y": 0.13675518062634942, 
                "x": 811.0
            }, 
            {
                "y": 0.1520940151549526, 
                "x": 812.0
            }, 
            {
                "y": 0.13049859521113769, 
                "x": 813.0
            }, 
            {
                "y": 0.12299545173069118, 
                "x": 814.0
            }, 
            {
                "y": 0.1245859724562729, 
                "x": 815.0
            }, 
            {
                "y": 0.13182215224682148, 
                "x": 816.0
            }, 
            {
                "y": 0.17770697818487544, 
                "x": 817.0
            }, 
            {
                "y": 0.16094960265566843, 
                "x": 818.0
            }, 
            {
                "y": 0.13239023088215668, 
                "x": 819.0
            }, 
            {
                "y": 0.12898096205662796, 
                "x": 820.0
            }, 
            {
                "y": 0.12450801790252569, 
                "x": 821.0
            }, 
            {
                "y": 0.138248534397714, 
                "x": 822.0
            }, 
            {
                "y": 0.12470638479607091, 
                "x": 823.0
            }, 
            {
                "y": 0.15147754951973896, 
                "x": 824.0
            }, 
            {
                "y": 0.13952086087339688, 
                "x": 825.0
            }, 
            {
                "y": 0.1726567057028761, 
                "x": 826.0
            }, 
            {
                "y": 0.15679006625584951, 
                "x": 827.0
            }, 
            {
                "y": 0.1317346258453007, 
                "x": 828.0
            }, 
            {
                "y": 0.11062658274401842, 
                "x": 829.0
            }, 
            {
                "y": 0.1828942199242165, 
                "x": 830.0
            }, 
            {
                "y": 0.1807416776613493, 
                "x": 831.0
            }, 
            {
                "y": 0.1318967898778938, 
                "x": 832.0
            }, 
            {
                "y": 0.12311692123829791, 
                "x": 833.0
            }, 
            {
                "y": 0.13276977180195473, 
                "x": 834.0
            }, 
            {
                "y": 0.12619833915803647, 
                "x": 835.0
            }, 
            {
                "y": 0.1370605712302921, 
                "x": 836.0
            }, 
            {
                "y": 0.14773894400957271, 
                "x": 837.0
            }, 
            {
                "y": 0.15553299029059753, 
                "x": 838.0
            }, 
            {
                "y": 0.16456942772732247, 
                "x": 839.0
            }, 
            {
                "y": 0.14019306248011032, 
                "x": 840.0
            }, 
            {
                "y": 0.13147675693398497, 
                "x": 841.0
            }, 
            {
                "y": 0.12059680591451549, 
                "x": 842.0
            }, 
            {
                "y": 0.13528138528138528, 
                "x": 843.0
            }, 
            {
                "y": 0.1441050011314777, 
                "x": 844.0
            }, 
            {
                "y": 0.13512829363709583, 
                "x": 845.0
            }, 
            {
                "y": 0.17602143627392247, 
                "x": 846.0
            }, 
            {
                "y": 0.16893623554699955, 
                "x": 847.0
            }, 
            {
                "y": 0.18313282668225592, 
                "x": 848.0
            }, 
            {
                "y": 0.13728562265381014, 
                "x": 849.0
            }, 
            {
                "y": 0.1652070020058971, 
                "x": 850.0
            }, 
            {
                "y": 0.2136540007690425, 
                "x": 851.0
            }, 
            {
                "y": 0.2878273771868278, 
                "x": 852.0
            }, 
            {
                "y": 0.2177503329700932, 
                "x": 853.0
            }, 
            {
                "y": 0.26664040961008273, 
                "x": 854.0
            }, 
            {
                "y": 0.283970939515081, 
                "x": 855.0
            }, 
            {
                "y": 0.29197721367667334, 
                "x": 856.0
            }, 
            {
                "y": 0.2989026215838375, 
                "x": 857.0
            }, 
            {
                "y": 0.3760141005287698, 
                "x": 858.0
            }, 
            {
                "y": 0.39493792937206224, 
                "x": 859.0
            }, 
            {
                "y": 0.37843393521044544, 
                "x": 860.0
            }, 
            {
                "y": 0.4855632040896366, 
                "x": 861.0
            }, 
            {
                "y": 0.688933513653812, 
                "x": 862.0
            }, 
            {
                "y": 0.6824812294239353, 
                "x": 863.0
            }, 
            {
                "y": 0.7433457009195029, 
                "x": 864.0
            }, 
            {
                "y": 0.8355366139194716, 
                "x": 865.0
            }, 
            {
                "y": 0.7768679208929137, 
                "x": 866.0
            }, 
            {
                "y": 0.6373681913207286, 
                "x": 867.0
            }, 
            {
                "y": 0.587091805940017, 
                "x": 868.0
            }, 
            {
                "y": 0.7442375579705129, 
                "x": 869.0
            }, 
            {
                "y": 1.0072053129567424, 
                "x": 870.0
            }, 
            {
                "y": 0.9560021727322109, 
                "x": 871.0
            }, 
            {
                "y": 0.9399946876584648, 
                "x": 872.0
            }, 
            {
                "y": 0.8539937462992011, 
                "x": 873.0
            }, 
            {
                "y": 0.5206982543640898, 
                "x": 874.0
            }, 
            {
                "y": 0.5226958941353893, 
                "x": 875.0
            }, 
            {
                "y": 0.4964138931420743, 
                "x": 876.0
            }, 
            {
                "y": 0.272767518815046, 
                "x": 877.0
            }, 
            {
                "y": 0.39670718548867806, 
                "x": 878.0
            }, 
            {
                "y": 0.4036949568024872, 
                "x": 879.0
            }, 
            {
                "y": 0.40477041346353615, 
                "x": 880.0
            }, 
            {
                "y": 0.713541822833898, 
                "x": 881.0
            }, 
            {
                "y": 0.8064473970812458, 
                "x": 882.0
            }, 
            {
                "y": 0.9154770630460832, 
                "x": 883.0
            }, 
            {
                "y": 0.6194793015674542, 
                "x": 884.0
            }, 
            {
                "y": 0.7754340850911029, 
                "x": 885.0
            }, 
            {
                "y": 0.5185823283288211, 
                "x": 886.0
            }, 
            {
                "y": 0.6347449614331924, 
                "x": 887.0
            }, 
            {
                "y": 0.6001384749691442, 
                "x": 888.0
            }, 
            {
                "y": 0.6925128934732349, 
                "x": 889.0
            }, 
            {
                "y": 0.5966153105791595, 
                "x": 890.0
            }, 
            {
                "y": 0.6201432304063133, 
                "x": 891.0
            }, 
            {
                "y": 1.033898305084746, 
                "x": 892.0
            }, 
            {
                "y": 1.5517320486350081, 
                "x": 893.0
            }, 
            {
                "y": 0.9011044599949413, 
                "x": 894.0
            }, 
            {
                "y": 0.8139315259956937, 
                "x": 895.0
            }, 
            {
                "y": 0.6593520193595377, 
                "x": 896.0
            }, 
            {
                "y": 0.8363668785265759, 
                "x": 897.0
            }, 
            {
                "y": 0.7021189079926198, 
                "x": 898.0
            }, 
            {
                "y": 0.7022299267197225, 
                "x": 899.0
            }, 
            {
                "y": 0.8276553664447478, 
                "x": 900.0
            }, 
            {
                "y": 0.5046731442924185, 
                "x": 901.0
            }, 
            {
                "y": 0.488584713442349, 
                "x": 902.0
            }, 
            {
                "y": 0.4768754237400795, 
                "x": 903.0
            }, 
            {
                "y": 0.4793908657348232, 
                "x": 904.0
            }, 
            {
                "y": 0.46559707117476046, 
                "x": 905.0
            }, 
            {
                "y": 0.6035680239684054, 
                "x": 906.0
            }, 
            {
                "y": 0.7576918255637425, 
                "x": 907.0
            }, 
            {
                "y": 0.8154948985121305, 
                "x": 908.0
            }, 
            {
                "y": 0.6545052515201768, 
                "x": 909.0
            }, 
            {
                "y": 0.6115315511515218, 
                "x": 910.0
            }, 
            {
                "y": 0.6682206253534335, 
                "x": 911.0
            }, 
            {
                "y": 0.5986914947156518, 
                "x": 912.0
            }, 
            {
                "y": 0.6860781247798955, 
                "x": 913.0
            }, 
            {
                "y": 0.7020868134333941, 
                "x": 914.0
            }, 
            {
                "y": 0.6042580270311397, 
                "x": 915.0
            }, 
            {
                "y": 0.6276244315747279, 
                "x": 916.0
            }, 
            {
                "y": 0.480058851347801, 
                "x": 917.0
            }, 
            {
                "y": 0.5881292219771683, 
                "x": 918.0
            }, 
            {
                "y": 0.6712706761186067, 
                "x": 919.0
            }, 
            {
                "y": 0.6157413797863236, 
                "x": 920.0
            }, 
            {
                "y": 0.6977639246510366, 
                "x": 921.0
            }, 
            {
                "y": 0.8929815828770532, 
                "x": 922.0
            }, 
            {
                "y": 0.880365296803653, 
                "x": 923.0
            }, 
            {
                "y": 0.7495080810411041, 
                "x": 924.0
            }, 
            {
                "y": 0.8089163122932822, 
                "x": 925.0
            }, 
            {
                "y": 0.8100851150954984, 
                "x": 926.0
            }, 
            {
                "y": 0.7345664252057105, 
                "x": 927.0
            }, 
            {
                "y": 0.7099660802196207, 
                "x": 928.0
            }, 
            {
                "y": 0.6853922417693211, 
                "x": 929.0
            }, 
            {
                "y": 0.6785671498742062, 
                "x": 930.0
            }, 
            {
                "y": 0.729548888409238, 
                "x": 931.0
            }, 
            {
                "y": 0.6529447280311763, 
                "x": 932.0
            }, 
            {
                "y": 0.6256995293768626, 
                "x": 933.0
            }, 
            {
                "y": 0.5969098077242047, 
                "x": 934.0
            }, 
            {
                "y": 0.6142404259018981, 
                "x": 935.0
            }, 
            {
                "y": 0.8704472106961733, 
                "x": 936.0
            }, 
            {
                "y": 0.8547222570009597, 
                "x": 937.0
            }, 
            {
                "y": 0.5612743218020505, 
                "x": 938.0
            }, 
            {
                "y": 0.6736941426233616, 
                "x": 939.0
            }, 
            {
                "y": 0.40899530820255625, 
                "x": 940.0
            }, 
            {
                "y": 0.28220142183470814, 
                "x": 941.0
            }, 
            {
                "y": 0.4337342772699154, 
                "x": 942.0
            }, 
            {
                "y": 0.3911753749361885, 
                "x": 943.0
            }, 
            {
                "y": 0.203377912401455, 
                "x": 944.0
            }, 
            {
                "y": 0.12460792700313655, 
                "x": 945.0
            }, 
            {
                "y": 0.0571999878813585, 
                "x": 946.0
            }, 
            {
                "y": 0.016263552960800665, 
                "x": 947.0
            }, 
            {
                "y": 0.006080449017773622, 
                "x": 948.0
            }, 
            {
                "y": 0.0028602073650339653, 
                "x": 949.0
            }, 
            {
                "y": 0.00046339202965709, 
                "x": 950.0
            }, 
            {
                "y": 0.009281875915974598, 
                "x": 951.0
            }, 
            {
                "y": 0.0049909963560055, 
                "x": 952.0
            }, 
            {
                "y": 0.005988023952095809, 
                "x": 953.0
            }, 
            {
                "y": 0.005457025920873125, 
                "x": 954.0
            }, 
            {
                "y": 0.012756264236902053, 
                "x": 955.0
            }, 
            {
                "y": 0.0076481835564053535, 
                "x": 956.0
            }, 
            {
                "y": 0.00795636431446287, 
                "x": 957.0
            }, 
            {
                "y": 0.034431137724550906, 
                "x": 958.0
            }, 
            {
                "y": 0.04241516966067865, 
                "x": 959.0
            }, 
            {
                "y": 0.03448275862068966, 
                "x": 960.0
            }, 
            {
                "y": 0.04241516966067864, 
                "x": 961.0
            }, 
            {
                "y": 0.04583538689009365, 
                "x": 962.0
            }, 
            {
                "y": 0.04940119760479042, 
                "x": 963.0
            }, 
            {
                "y": 0.053393213572854294, 
                "x": 964.0
            }, 
            {
                "y": 0.04640718562874253, 
                "x": 965.0
            }
        ], 
        "name": "IPC"
    }
]